sbucket/__init__.py
sbucket/main.py
sbucket/s3bucket.py
sbucket/s3file.py
smart_bucket-0.1.0.dist-info/LICENSE
smart_bucket-0.1.0.dist-info/METADATA
smart_bucket-0.1.0.dist-info/WHEEL
smart_bucket-0.1.0.dist-info/entry_points.txt
smart_bucket-0.1.0.dist-info/top_level.txt
smart_bucket-0.1.0.dist-info/RECORD
