Metadata-Version: 2.1
Name: smart-bucket
Version: 0.1.0
Summary: Bidirectional synchronization between local directory and s3 bucket.
Author-email: Bjorn Pettersen <bp@datakortet.no>
License: MIT License
Project-URL: homepage, https://github.com/thebjorn/smart-bucket
Project-URL: repository, https://github.com/thebjorn/smart-bucket
Project-URL: documentation, https://smart-bucket.readthedocs.io/en/latest/
Project-URL: issues, https://github.com/thebjorn/smart-bucket/issues
Keywords: s3,sync,aws
Classifier: Development Status :: 3 - Alpha
Classifier: Environment :: Console
Classifier: Intended Audience :: Developers
Classifier: License :: OSI Approved :: MIT License
Classifier: Operating System :: OS Independent
Classifier: Programming Language :: Python :: 3
Classifier: Topic :: Software Development :: Libraries :: Python Modules
Classifier: Topic :: Utilities
Requires-Python: >=3.7
License-File: LICENSE
Requires-Dist: boto3
Requires-Dist: click
Requires-Dist: click-log
Requires-Dist: click-spinner
Requires-Dist: click-threading
Requires-Dist: humanize
Requires-Dist: pyyaml
Requires-Dist: smart-open
Requires-Dist: tqdm
